{
  "word": "lane",
  "analysis": "### 分析词义\n\n\"Lane\" 是一个名词，主要指“车道”或“小路”。在不同的上下文中，它可以表示车辆行驶的道路部分，也可以指乡村或城市中的狭窄小路。\n\n### 列举例句\n\n1. **Driving on the highway:**  \n   \"Please stay in your lane while driving on the highway.\"  \n   **中文翻译:** “在高速公路上行驶时，请保持在您的车道内。”\n\n2. **Walking in a rural area:**  \n   \"We found a quiet lane behind the village.\"  \n   **中文翻译:** “我们在村庄后面发现了一条安静的小路。”\n\n3. **Swimming competition:**  \n   \"The swimmer was disqualified for crossing into another lane.\"  \n   **中文翻译:** “这位游泳运动员因进入另一泳道而被取消资格。”\n\n### 词根分析\n\n- **词根:** \"Lane\" 源自中古英语的 \"lane\"，进一步追溯到古英语的 \"lang\"，意为“长”或“狭长”。这个词根强调了道路或路径的狭长特征。\n- **衍生单词:** 由于 \"lane\" 本身是一个基本词汇，没有太多直接的衍生单词，但可以与其他词组合形成新的词汇，如 \"alley lane\"（小巷）。\n\n### 词缀分析\n\n- **无明显词缀:** \"Lane\" 是一个独立的单词，没有明显的前缀、后缀或中缀。它是一个基础词汇，主要通过上下文来确定其具体含义。\n- **相同词缀的单词:** 由于 \"lane\" 没有明显的词缀结构，因此无法列出具有相同词缀的其他单词。\n\n### 发展历史和文化背景\n\n- **造词来源:** \"Lane\" 的历史可以追溯到古代英语时期，最初用于描述狭长的路径或道路。随着城市和交通的发展，这个词逐渐被用来指代车辆行驶的道路部分。在现代英语中，\"lane\" 广泛用于描述各种类型的道路和路径。\n- **文化内涵:** 在欧美文化中，\"lane\" 常与乡村生活、宁静和自然联系在一起。例如，乡村小路（country lane）常被视为宁静和美丽的象征。在交通文化中，\"lane\" 是道路安全的重要概念，驾驶员需要严格遵守车道规则以确保安全驾驶。\n\n### 单词变形\n\n- **名词形式:** lane (单数), lanes (复数)  \n- **动词形式:** 无直接动词形式  \n- **形容词形式:** lanelike (类似小路的)  \n- **副词形式:** 无直接副词形式  \n- **固定搭配:**  \n  - \"keep to your lane\": 保持在你的车道内  \n    **中文翻译:** 保持在你的车道内  \n  - \"single lane\": 单车道  \n    **中文翻译:** 单车道  ",
  "draw_explain": "选择跑道作为视觉线索，因为跑道是'lane'的一个常见且易于联想的含义。通过描绘一个清晰的跑道图像，可以帮助用户快速记住'lane'与跑道相关的含义。",
  "draw_prompt": "A clear, well-defined running track with white lines and a grassy infield, surrounded by a quiet, sunny countryside."
}